monoid/__init__.py
monoid-0.1.0a0.dist-info/WHEEL
monoid-0.1.0a0.dist-info/METADATA
monoid-0.1.0a0.dist-info/RECORD
